{
    "imposter-packs": [
        {
            "pack-name": "household-names",
            "pack-path": "/json-files/party-games/questions/imposter/household-names.json",
            "pack-card": "/images/blank-cards/imposter-blank-card.svg",
            "pack-colour": "var(--primarypagecolour)",
            "pack-secondary-colour": "var(--secondarypagecolour)",
            "pack-difficulty": "chill, creative, funny, deep",
            "pack-restriction": "sfw",
            "pack-active": true
        }
    ]
}