{
    "never-have-i-ever-packs": [
        {
            "pack-name": "simple-admissions",
            "pack-path": "/json-files/party-games/questions/never-have-i-ever/simple-admissions.json",
            "pack-card": "/images/blank-cards/never-have-i-ever-blank-card.svg",
            "pack-colour": "var(--primarypagecolour)",
            "pack-secondary-colour": "var(--secondarypagecolour)",
            "pack-difficulty": 1,
            "pack-restriction": "sfw",
            "pack-active": true
        },
        {
            "pack-name": "rising-suspicions",
            "pack-path": "/json-files/party-games/questions/never-have-i-ever/rising-suspicions.json",
            "pack-card": "/images/blank-cards/never-have-i-ever-blank-card.svg",
            "pack-colour": "var(--primarypagecolour)",
            "pack-secondary-colour": "var(--secondarypagecolour)",
            "pack-difficulty": 2,
            "pack-restriction": "sfw",
            "pack-active": true
        },
        {
            "pack-name": "digging-deeper",
            "pack-path": "/json-files/party-games/questions/never-have-i-ever/digging-deeper.json",
            "pack-card": "/images/blank-cards/never-have-i-ever-blank-card.svg",
            "pack-colour": "var(--primarypagecolour)",
            "pack-secondary-colour": "var(--secondarypagecolour)",
            "pack-difficulty": 3,
            "pack-restriction": "sfw",
            "pack-active": true
        },
        {
            "pack-name": "verbal-diarrhea",
            "pack-path": "/json-files/party-games/questions/never-have-i-ever/verbal-diarrhea.json",
            "pack-card": "/images/blank-cards/never-have-i-ever-blank-card.svg",
            "pack-colour": "var(--primarypagecolour)",
            "pack-secondary-colour": "var(--secondarypagecolour)",
            "pack-difficulty": 4,
            "pack-restriction": "nsfw",
            "pack-active": true
        },
        {
            "pack-name": "raw-and-unfiltered",
            "pack-path": "/json-files/party-games/questions/never-have-i-ever/raw-and-unfiltered.json",
            "pack-card": "/images/blank-cards/never-have-i-ever-blank-card.svg",
            "pack-colour": "var(--primarypagecolour)",
            "pack-secondary-colour": "var(--secondarypagecolour)",
            "pack-difficulty": 5,
            "pack-restriction": "nsfw",
            "pack-active": true
        }
    ]
}